number_system_float/Binary.py
number_system_float/Hexadecimal.py
number_system_float/Octal.py
number_system_float/__init__.py
number_system_float-0.10.0.dist-info/licenses/LICENSE.txt
number_system_float-0.10.0.dist-info/METADATA
number_system_float-0.10.0.dist-info/WHEEL
number_system_float-0.10.0.dist-info/top_level.txt
number_system_float-0.10.0.dist-info/RECORD
