Metadata-Version: 2.4
Name: number_system_float
Version: 0.10.0
Summary: A project for floating-point numbers in the binary, octal, and hexadecimal systems.
Author-email: William Brady Call <wbradycall@gmail.com>
Project-URL: Homepage, https://github.com/wbradycall/NumberSystemFloat
Keywords: binary,octal,hexidecimal,float,number
Requires-Python: >=3.8
License-File: LICENSE.txt
Dynamic: license-file
